AUTHORS.rst
CONTRIBUTING.rst
HISTORY.rst
LICENSE
MANIFEST.in
README
README.rst
setup.cfg
setup.py
cybak.egg-info/PKG-INFO
cybak.egg-info/SOURCES.txt
cybak.egg-info/dependency_links.txt
cybak.egg-info/not-zip-safe
cybak.egg-info/pbr.json
cybak.egg-info/requires.txt
cybak.egg-info/top_level.txt
dirwalker/__init__.py
dirwalker/dirwalker.py
docs/Makefile
docs/authors.rst
docs/conf.py
docs/contributing.rst
docs/history.rst
docs/index.rst
docs/installation.rst
docs/make.bat
docs/readme.rst
docs/usage.rst
scripts/cybak
tests/test_cybak-lzma.py
tests/test_cybak-lzma.py~
tests/test_dirwalker.py
tests/test_dirwalker.py~