Metadata-Version: 1.1
Name: cybak
Version: 0.4.3
Summary: A simple backup script for Debian.
Home-page: https://github.com/iansmcf/cybak-lzma
Author: Ian McFarlane
Author-email: iansmcfarlane@gmail.com
License: BSD
Keywords: cybackup
Platform: UNKNOWN
Classifier: Development Status :: 2 - Pre-Alpha
Classifier: Intended Audience :: Developers
Classifier: License :: OSI Approved :: BSD License
Classifier: Natural Language :: English
Classifier: Programming Language :: Python :: 2.7
